tee_logfile/__init__.py
tee_logfile/tee.py
tee_logfile-0.3.9.dist-info/METADATA
tee_logfile-0.3.9.dist-info/WHEEL
tee_logfile-0.3.9.dist-info/RECORD
