Metadata-Version: 2.4
Name: tee-logfile
Version: 0.3.9
Summary: A simple utility to tee stdout and stderr to a logfile.
Author: cy
Requires-Python: >=3.9
Classifier: Programming Language :: Python :: 3
Classifier: Programming Language :: Python :: 3.9
Classifier: Programming Language :: Python :: 3.10
Classifier: Programming Language :: Python :: 3.11
Classifier: Programming Language :: Python :: 3.12
Classifier: Programming Language :: Python :: 3.13
Classifier: Programming Language :: Python :: 3.14
Project-URL: Repository, https://github.com/firstim21cy/tee-logfile
